simple_uu/__init__.py
simple_uu/decode.py
simple_uu/encode.py
simple_uu/exceptions.py
simple_uu/logger.py
simple_uu/py.typed
simple_uu/types.py
simple_uu/utils.py
simple_uu-0.2.0.dist-info/LICENSE
simple_uu-0.2.0.dist-info/METADATA
simple_uu-0.2.0.dist-info/WHEEL
simple_uu-0.2.0.dist-info/RECORD
