Metadata-Version: 2.1
Name: simple-uu
Version: 0.2.0
Summary: Includes easy-to-use functions to encode/decode binary data to/from UU format. In addition, includes a structured and intuitive interface for seamless extraction of content and metadata, emphasizing user ease and the organized handling of Uuencoded data.
License: MIT
Keywords: uu,uuencoded,encoding,decoding
Author: galactixx
Requires-Python: >=3.10,<4.0
Classifier: License :: OSI Approved :: MIT License
Classifier: Programming Language :: Python :: 3
Classifier: Programming Language :: Python :: 3.10
Classifier: Programming Language :: Python :: 3.11
Classifier: Programming Language :: Python :: 3.12
Requires-Dist: charset-normalizer (>=3.3.2,<4.0.0)
Requires-Dist: filetype (>=1.2.0,<2.0.0)
Requires-Dist: rich (>=13.7.1,<14.0.0)
Requires-Dist: unix-perms (>=0.4.0,<0.5.0)
